pydantic_enhanced_serializer/__init__.py
pydantic_enhanced_serializer/fieldsets.py
pydantic_enhanced_serializer/models.py
pydantic_enhanced_serializer/path_put.py
pydantic_enhanced_serializer/py.typed
pydantic_enhanced_serializer/render.py
pydantic_enhanced_serializer/schema.py
pydantic_enhanced_serializer/integrations/__init__.py
pydantic_enhanced_serializer/integrations/django_ninja.py
pydantic_enhanced_serializer/integrations/fastapi.py
pydantic_enhanced_serializer-2.2.2.dist-info/licenses/LICENSE
pydantic_enhanced_serializer-2.2.2.dist-info/METADATA
pydantic_enhanced_serializer-2.2.2.dist-info/WHEEL
pydantic_enhanced_serializer-2.2.2.dist-info/top_level.txt
pydantic_enhanced_serializer-2.2.2.dist-info/RECORD
