Metadata-Version: 2.4
Name: pydantic-enhanced-serializer
Version: 2.2.2
Summary: Pydantic extension that allows user selection of object fields or expansions inline when serializing models
Home-page: https://github.com/adamsussman/pydantic-enhanced-serializer
Author: Adam Sussman
Author-email: adam.sussman@gmail.com
License: MIT
Classifier: Development Status :: 5 - Production/Stable
Classifier: Framework :: Pydantic
Classifier: Framework :: FastAPI
Classifier: Framework :: Flask
Classifier: Framework :: Django
Classifier: Intended Audience :: Developers
Classifier: License :: OSI Approved :: MIT License
Classifier: Operating System :: OS Independent
Classifier: Programming Language :: Python :: 3 :: Only
Classifier: Programming Language :: Python :: 3.11
Classifier: Programming Language :: Python :: 3.10
Classifier: Programming Language :: Python :: 3.8
Classifier: Programming Language :: Python :: 3.9
Classifier: Topic :: Software Development :: Libraries :: Python Modules
Classifier: Topic :: Internet
License-File: LICENSE
Requires-Dist: pydantic>=2.5
Requires-Dist: packaging>=24.2
Provides-Extra: test
Requires-Dist: asgiref; extra == "test"
Requires-Dist: aiodataloader; extra == "test"
Requires-Dist: django; extra == "test"
Requires-Dist: fastapi; extra == "test"
Requires-Dist: flask; extra == "test"
Requires-Dist: httpx; extra == "test"
Requires-Dist: pytest; extra == "test"
Requires-Dist: pytest-cov; extra == "test"
Requires-Dist: requests<3.0.0,>=2.24.0; extra == "test"
Provides-Extra: dev
Requires-Dist: mypy; extra == "dev"
Requires-Dist: black; extra == "dev"
Requires-Dist: isort; extra == "dev"
Requires-Dist: flake8; extra == "dev"
Requires-Dist: flake8-bugbear; extra == "dev"
Requires-Dist: flake8-debugger; extra == "dev"
Requires-Dist: ipdb; extra == "dev"
Dynamic: license-file
